README.txt
setup.cfg
setup.py
Slingr.egg-info/PKG-INFO
Slingr.egg-info/SOURCES.txt
Slingr.egg-info/dependency_links.txt
Slingr.egg-info/entry_points.txt
Slingr.egg-info/not-zip-safe
Slingr.egg-info/requires.txt
Slingr.egg-info/top_level.txt
slingr/__init__.py
slingr/asset.py
slingr/build.py
slingr/coburl.py
slingr/common.py
slingr/config.py
slingr/eggsac_config.py
slingr/json2yaml.py
slingr/make_view.py
slingr/manage.py
slingr/node.py
slingr/runtime.py
slingr/server.py
slingr/setup_cob.py
slingr/watch.py
slingr/wsgi_app.py
slingr/testsuite/__init__.py
slingr/testsuite/test_asset.py
slingr/testsuite/test_build.py
slingr/testsuite/test_coburl.py
slingr/testsuite/test_common.py
slingr/testsuite/test_config.py
slingr/testsuite/test_node.py
slingr/testsuite/test_watch.py