Metadata-Version: 1.1
Name: Slingr
Version: 0.0.13
Summary: Web development framework that builds and serves Cobs (deployable web applications), running on top of Flask
Home-page: https://github.com/cozi/slingr
Author: George V. Reilly
Author-email: george@reilly.org
License: MIT License
Platform: any
Classifier: Development Status :: 4 - Beta
Classifier: Environment :: Console
Classifier: Framework :: Flask
Classifier: Intended Audience :: Developers
Classifier: License :: OSI Approved :: MIT License
Classifier: Operating System :: OS Independent
Classifier: Programming Language :: Python
Classifier: Topic :: Internet :: WWW/HTTP :: Dynamic Content
